README.md
setup.py
neptune_cache_redis/__init__.py
neptune_cache_redis/cache.py
neptune_cache_redis/connect.py
neptune_cache_redis.egg-info/PKG-INFO
neptune_cache_redis.egg-info/SOURCES.txt
neptune_cache_redis.egg-info/dependency_links.txt
neptune_cache_redis.egg-info/requires.txt
neptune_cache_redis.egg-info/top_level.txt