Metadata-Version: 2.1
Name: neptune-cache-redis
Version: 2019.9.14.2111
Summary: REDIS CACHE FOR NEPTUNE DNS SERVER
Home-page: https://git.best-service.online/yurzs/neptune-cache-redis
Author: Yury (Yurzs)
Author-email: dev@best-service.online
License: MIT
Keywords: NEPTUNE,CACHE,REDIS
Platform: UNKNOWN
Classifier: Development Status :: 3 - Alpha
Classifier: Intended Audience :: Developers
Classifier: Topic :: Software Development :: Build Tools
Classifier: License :: OSI Approved :: MIT License
Classifier: Programming Language :: Python :: 3
Classifier: Programming Language :: Python :: 3.7
Classifier: Programming Language :: Python :: 3.5
Classifier: Programming Language :: Python :: 3.6
